certbot_dns_ispmanager/__init__.py
certbot_dns_ispmanager/dns_ispmanager.py
certbot_dns_ispmanager-0.11.dist-info/AUTHORS.rst
certbot_dns_ispmanager-0.11.dist-info/LICENSE
certbot_dns_ispmanager-0.11.dist-info/METADATA
certbot_dns_ispmanager-0.11.dist-info/WHEEL
certbot_dns_ispmanager-0.11.dist-info/entry_points.txt
certbot_dns_ispmanager-0.11.dist-info/top_level.txt
certbot_dns_ispmanager-0.11.dist-info/RECORD
